nanorlhf/__init__.py
nanorlhf/eval/__init__.py
nanorlhf/eval/math_eval.py
nanorlhf/eval/utils.py
nanorlhf/kernels/__init__.py
nanorlhf/kernels/api.py
nanorlhf/kernels/patch.py
nanorlhf/kernels/flash_attn/__init__.py
nanorlhf/kernels/flash_attn/bwd.py
nanorlhf/kernels/flash_attn/fwd.py
nanorlhf/kernels/flash_attn/ops.py
nanorlhf/kernels/flash_attn_decode/__init__.py
nanorlhf/kernels/flash_attn_decode/ops.py
nanorlhf/kernels/flash_attn_decode/reduce_k.py
nanorlhf/kernels/flash_attn_decode/split_k.py
nanorlhf/kernels/flash_attn_varlen/__init__.py
nanorlhf/kernels/flash_attn_varlen/bwd.py
nanorlhf/kernels/flash_attn_varlen/fwd.py
nanorlhf/kernels/flash_attn_varlen/ops.py
nanorlhf/kernels/kvcache/__init__.py
nanorlhf/kernels/kvcache/load.py
nanorlhf/kernels/kvcache/store.py
nanorlhf/kernels/rmsnorm/__init__.py
nanorlhf/kernels/rmsnorm/bwd.py
nanorlhf/kernels/rmsnorm/fwd.py
nanorlhf/kernels/rmsnorm/ops.py
nanorlhf/kernels/utils/__init__.py
nanorlhf/kernels/utils/huggingface.py
nanorlhf/kernels/utils/padding.py
nanorlhf/kernels/utils/vllm.py
nanorlhf/nanoray/__init__.py
nanorlhf/nanoray/utils.py
nanorlhf/nanoray/api/__init__.py
nanorlhf/nanoray/api/initialization.py
nanorlhf/nanoray/api/remote.py
nanorlhf/nanoray/api/session.py
nanorlhf/nanoray/core/__init__.py
nanorlhf/nanoray/core/object_ref.py
nanorlhf/nanoray/core/object_store.py
nanorlhf/nanoray/core/placement.py
nanorlhf/nanoray/core/runtime_env.py
nanorlhf/nanoray/core/serialization.py
nanorlhf/nanoray/core/task.py
nanorlhf/nanoray/network/__init__.py
nanorlhf/nanoray/network/proxy.py
nanorlhf/nanoray/network/router.py
nanorlhf/nanoray/network/rpc_client.py
nanorlhf/nanoray/network/rpc_server.py
nanorlhf/nanoray/runtime/__init__.py
nanorlhf/nanoray/runtime/actor.py
nanorlhf/nanoray/runtime/messages.py
nanorlhf/nanoray/runtime/worker.py
nanorlhf/nanoray/scheduler/__init__.py
nanorlhf/nanoray/scheduler/node_state.py
nanorlhf/nanoray/scheduler/policies.py
nanorlhf/nanoray/scheduler/scheduler.py
nanorlhf-1.0.0.dist-info/licenses/LICENSE
nanorlhf-1.0.0.dist-info/METADATA
nanorlhf-1.0.0.dist-info/WHEEL
nanorlhf-1.0.0.dist-info/top_level.txt
nanorlhf-1.0.0.dist-info/RECORD
