Metadata-Version: 2.4
Name: nanorlhf
Version: 1.0.0
Summary: nanoRLHF: from-scratch journey into how LLMs and RLHF really work.
Author-email: hyunwoongko <gusdnd852@naver.com>
License:                                  Apache License
Project-URL: Homepage, https://github.com/hyunwoongko/nanorlhf
Project-URL: Repository, https://github.com/hyunwoongko/nanorlhf
Keywords: rlhf,rl,llm,language model,deep learning,ai
Requires-Python: >=3.9
License-File: LICENSE
Requires-Dist: torch
Requires-Dist: triton==3.4.0
Requires-Dist: transformers==4.57.3
Requires-Dist: cloudpickle==3.1.1
Requires-Dist: zstandard==0.25.0
Requires-Dist: wandb==0.17.9
Requires-Dist: math-verify==0.8.0
Dynamic: license-file
